tiktok_creator_mcp/__init__.py
tiktok_creator_mcp/server.py
tiktok_creator_mcp/tiktok_api.py
tiktok_creator_mcp-1.0.0.dist-info/METADATA
tiktok_creator_mcp-1.0.0.dist-info/WHEEL
tiktok_creator_mcp-1.0.0.dist-info/entry_points.txt
tiktok_creator_mcp-1.0.0.dist-info/RECORD
