Metadata-Version: 2.4
Name: tiktok-creator-mcp
Version: 1.0.0
Summary: TikTok automation MCP: post videos, get analytics, manage comments
Project-URL: Homepage, https://github.com/MarceauSolutions/dev-sandbox/tree/main/projects/tiktok-creator
Project-URL: Repository, https://github.com/MarceauSolutions/dev-sandbox
Author-email: "William Marceau Jr." <william@marceausolutions.com>
License-Expression: MIT
Keywords: automation,creator,mcp,social,tiktok,video
Classifier: Development Status :: 4 - Beta
Classifier: Intended Audience :: Developers
Classifier: License :: OSI Approved :: MIT License
Classifier: Programming Language :: Python :: 3
Classifier: Programming Language :: Python :: 3.10
Classifier: Programming Language :: Python :: 3.11
Classifier: Programming Language :: Python :: 3.12
Requires-Python: >=3.10
Requires-Dist: mcp>=1.0.0
Requires-Dist: requests>=2.28.0
